canicve/__init__.py
canicve/plugin.py
canicve/templates/canicve.template
mkdocs_canicve_plugin-1.0.0.dist-info/LICENSE.md
mkdocs_canicve_plugin-1.0.0.dist-info/METADATA
mkdocs_canicve_plugin-1.0.0.dist-info/WHEEL
mkdocs_canicve_plugin-1.0.0.dist-info/entry_points.txt
mkdocs_canicve_plugin-1.0.0.dist-info/top_level.txt
mkdocs_canicve_plugin-1.0.0.dist-info/RECORD
