Metadata-Version: 2.1
Name: mkdocs-canicve-plugin
Version: 1.0.0
Summary: "Create a searchable coverage table in mkdocs"
Home-page: https://github.com/canicve/mkdocs-canicve-plugin
Author: ArchiMoebius
Author-email: rhiza@canicve.com
License: MIT
Keywords: "mkdocs python markdown table for canicve"
Platform: UNKNOWN
Classifier: Intended Audience :: Developers
Classifier: License :: OSI Approved :: MIT License
Classifier: Operating System :: OS Independent
Classifier: Intended Audience :: Information Technology
Classifier: Programming Language :: Python :: 3.6
Classifier: Programming Language :: Python :: 3.7
Classifier: Programming Language :: Python :: 3.8
Requires-Python: >=3.6
Requires-Dist: mkdocs (==1.2.3)
